README.md
setup.cfg
setup.py
distributions2_DarioDitano/Binomialdistribution.py
distributions2_DarioDitano/Gaussiandistribution.py
distributions2_DarioDitano/Generaldistribution.py
distributions2_DarioDitano/__init__.py
distributions2_DarioDitano.egg-info/PKG-INFO
distributions2_DarioDitano.egg-info/SOURCES.txt
distributions2_DarioDitano.egg-info/dependency_links.txt
distributions2_DarioDitano.egg-info/not-zip-safe
distributions2_DarioDitano.egg-info/top_level.txt